create_tg_bot/__init__.py
create_tg_bot/constants.py
create_tg_bot/main.py
create_tg_bot/texts.py
create_tg_bot/cli/__init__.py
create_tg_bot/cli/database.py
create_tg_bot/cli/env.py
create_tg_bot/cli/tokens.py
create_tg_bot/templates/.env.jinja
create_tg_bot/templates/.gitignore.jinja
create_tg_bot/templates/Dockerfile.jinja
create_tg_bot/templates/Makefile.jinja
create_tg_bot/templates/__init__.py
create_tg_bot/templates/alembic.ini.jinja
create_tg_bot/templates/config.py.jinja
create_tg_bot/templates/docker-compose.yml.jinja
create_tg_bot/templates/main.py.jinja
create_tg_bot/templates/manage.py.jinja
create_tg_bot/templates/requirements.txt.jinja
create_tg_bot/templates/.github/workflows/ci-cd.yml.jinja
create_tg_bot/templates/button_handlers/page.py.jinja
create_tg_bot/templates/commands/log.py.jinja
create_tg_bot/templates/commands/op.py.jinja
create_tg_bot/templates/commands/parse_args.py.jinja
create_tg_bot/templates/commands/start.py.jinja
create_tg_bot/templates/commands/users.py.jinja
create_tg_bot/templates/commands/who_am_i.py.jinja
create_tg_bot/templates/core/module_loader.py.jinja
create_tg_bot/templates/core/generator_templates/button_handler.py.jinja
create_tg_bot/templates/core/generator_templates/command.py.jinja
create_tg_bot/templates/core/generator_templates/keyboard.py.jinja
create_tg_bot/templates/core/generator_templates/model.py.jinja
create_tg_bot/templates/crud/find_or_create_user.py.jinja
create_tg_bot/templates/crud/find_user_by_id.py.jinja
create_tg_bot/templates/crud/get_user_list_with_pagination.py.jinja
create_tg_bot/templates/keyboards/pagination_keyboard.py.jinja
create_tg_bot/templates/migrations/env.py.jinja
create_tg_bot/templates/migrations/script.py.mako.jinja
create_tg_bot/templates/models/User.py.jinja
create_tg_bot/templates/models/base.py.jinja
create_tg_bot/templates/other_handlers/random_text_handler.py.jinja
create_tg_bot/templates/services/db.py.jinja
create_tg_bot/templates/texts/formatters.py.jinja
create_tg_bot-0.1.4.dist-info/licenses/LICENSE
create_tg_bot-0.1.4.dist-info/METADATA
create_tg_bot-0.1.4.dist-info/WHEEL
create_tg_bot-0.1.4.dist-info/entry_points.txt
create_tg_bot-0.1.4.dist-info/top_level.txt
create_tg_bot-0.1.4.dist-info/RECORD
