Metadata-Version: 2.4
Name: create-tg-bot
Version: 0.1.4
Summary: A modular, CLI-first Python boilerplate for building Telegram bots. Fast setup, clean architecture, and open-source ready.
Home-page: https://github.com/emilastanov/create-tg-bot
Author: Emil Astanov
Author-email: emila1998@yandex.ru
License: MIT
Keywords: telegram,bot,telegram-bot,cli,command-line,python,boilerplate,template,starter-kit,open-source,asyncio,telegram-cli,modular,framework,python3,telegram-api,telegram-bot-api
Classifier: Development Status :: 3 - Alpha
Classifier: Intended Audience :: Developers
Classifier: License :: OSI Approved :: MIT License
Classifier: Programming Language :: Python
Classifier: Programming Language :: Python :: 3
Classifier: Programming Language :: Python :: 3.7
Classifier: Programming Language :: Python :: 3.8
Classifier: Programming Language :: Python :: 3.9
Classifier: Programming Language :: Python :: 3.10
Classifier: Programming Language :: Python :: 3.11
Classifier: Environment :: Console
Classifier: Operating System :: OS Independent
Classifier: Topic :: Utilities
Classifier: Topic :: Software Development :: Build Tools
Requires-Python: >=3.7
License-File: LICENSE
Requires-Dist: click
Requires-Dist: jinja2
Dynamic: author
Dynamic: author-email
Dynamic: classifier
Dynamic: description
Dynamic: description-content-type
Dynamic: home-page
Dynamic: keywords
Dynamic: license
Dynamic: license-file
Dynamic: requires-dist
Dynamic: requires-python
Dynamic: summary
